tailraiders/__init__.py
tailraiders/boaboa/__init__.py
tailraiders/boaboa/doc.py
tailraiders/bugtrapper/__init__.py
tailraiders/gajalaka/__init__.py
tailraiders/gajalaka/nan.py
tailraiders/gajalaka/plots.py
tailraiders/plunderer/__init__.py
tailraiders/protector/__init__.py
tailraiders/protector/nan.py
tailraiders/protector/prep.py
tailraiders/trouper/__init__.py
tailraiders-0.1.0.dist-info/LICENSE
tailraiders-0.1.0.dist-info/METADATA
tailraiders-0.1.0.dist-info/WHEEL
tailraiders-0.1.0.dist-info/top_level.txt
tailraiders-0.1.0.dist-info/RECORD
