Metadata-Version: 2.1
Name: tailraiders
Version: 0.1.0
Summary: A package for making Data Science easier
Author: Busse Heemskerk
License: UNKNOWN
Platform: UNKNOWN
Requires-Python: >=2.7, !=3.0.*, !=3.1.*
License-File: LICENSE
Requires-Dist: pandas (>=1.0)
Requires-Dist: numpy (>=1.0)
Requires-Dist: matplotlib (>=2.2.3)
Requires-Dist: seaborn (>=0.9.0)
